evenstar/__init__.py
evenstar/types.py
palantir/__init__.py
palantir/types.py
evenstar-0.2.dist-info/METADATA
evenstar-0.2.dist-info/WHEEL
evenstar-0.2.dist-info/top_level.txt
evenstar-0.2.dist-info/RECORD
