Metadata-Version: 2.1
Name: evenstar
Version: 0.2
Summary: A GraphQL query builder
Home-page: https://github.com/Yaser-Amiri/evenstar
Author: Yaser Amiri
Author-email: yaser.amiri95@gmail.com
License: MIT
Keywords: graphql
Platform: UNKNOWN
Classifier: Programming Language :: Python :: 3
Classifier: License :: OSI Approved :: MIT License
Classifier: Operating System :: OS Independent
Classifier: Topic :: Software Development :: Object Brokering
Classifier: Topic :: Software Development :: Libraries
Classifier: Topic :: Software Development
